Workbook

Sheet Sheet1
A1: round | B1: model | C1: time_horizon | D1: temperature | E1: Technology_label | F1: Domain | G1: Domain_manual | H1: Explanation | I1: json_line | J1: adoption_prob_1 | K1: adoption_prob_2 | L1: adoption_prob_3 | M1: adoption_prob_4 | N1: adoption_prob_5 | O1: adoption_prob_6 | P1: adoption_prob_7 | Q1: adoption_prob_8 | R1: adoption_prob_9 | S1: adoption_prob_10 | T1: avg_probs
A2: 1 | B2: gpt-5.2 | C2: next year | D2: 0.7 | E2: On-device small AI models | F2: AI / Edge computing | G2: =INDEX(Sheet2!A:B,MATCH(Sheet1!F2,Sheet2!A:A,0),2) -> AI & Data Technologies | H2: Smaller language and vision models run directly on phones, laptops, and industrial devices, reducing cloud costs and improving privacy and latency. Organizations can adopt them for offline support, secure document handling, and real-time inspection, but performance varies widely by hardware and model quality. | I2: [{"Technology_label": "On-device small AI models", "Domain": "AI / Edge computing", "Uncertainty_explanation": "Smaller language and vision models run directly on phones, laptops, and industrial devices, reducing cloud costs and improving privacy and latency. Organizations can adopt them for offline support, secure document handling, and real-time inspection, but performance varies widely by hardware and model quality."}] | J2: 82 | K2: 85 | L2: 82 | M2: 82 | N2: 88 | O2: 82 | P2: 82 | Q2: 85 | R2: 85 | S2: 85 | T2: =AVERAGE(J2:S2) -> 83.8 | V2: Row Labels | W2: Average of avg_probs
A3: 1 | B3: gpt-5.2 | C3: next year | D3: 0.7 | E3: Retrieval-augmented generation (RAG) | F3: AI / Knowledge management | G3: =INDEX(Sheet2!A:B,MATCH(Sheet1!F3,Sheet2!A:A,0),2) -> AI & Data Technologies | H3: RAG systems connect generative AI to vetted internal documents and databases so answers can cite sources and reflect current policies. Adoption is accelerating in customer support and internal copilots, though outcomes depend on data quality, access controls, and governance against hallucinations. | I3: [{"Technology_label": "Retrieval-augmented generation (RAG)", "Domain": "AI / Knowledge management", "Uncertainty_explanation": "RAG systems connect generative AI to vetted internal documents and databases so answers can cite sources and reflect current policies. Adoption is accelerating in customer support and internal copilots, though outcomes depend on data quality, access controls, and governance against hallucinations."}] | J3: 88 | K3: 88 | L3: 88 | M3: 88 | N3: 92 | O3: 90 | P3: 90 | Q3: 92 | R3: 92 | S3: 88 | T3: =AVERAGE(J3:S3) -> 89.6 | V3: next 20–40 years | W3: 53.902
A4: 1 | B4: gpt-5.2 | C4: next year | D4: 0.7 | E4: Synthetic data generation tools | F4: Data / Privacy | G4: =INDEX(Sheet2!A:B,MATCH(Sheet1!F4,Sheet2!A:A,0),2) -> Governance, Finance & Law | H4: Synthetic data tools create realistic but artificial datasets to train models or test systems when real data is sensitive or scarce. They can speed analytics and compliance, yet there is uncertainty about how well synthetic data preserves rare events and whether it can still leak sensitive patterns. | I4: [{"Technology_label": "Synthetic data generation tools", "Domain": "Data / Privacy", "Uncertainty_explanation": "Synthetic data tools create realistic but artificial datasets to train models or test systems when real data is sensitive or scarce. They can speed analytics and compliance, yet there is uncertainty about how well synthetic data preserves rare events and whether it can still leak sensitive patterns."}] | J4: 78 | K4: 78 | L4: 78 | M4: 78 | N4: 78 | O4: 78 | P4: 78 | Q4: 78 | R4: 78 | S4: 78 | T4: =AVERAGE(J4:S4) -> 78 | V4: next 5–10 years | W4: 70.499
A5: 1 | B5: gpt-5.2 | C5: next year | D5: 0.7 | E5: Privacy-enhancing computation (PETs) | F5: Cybersecurity / Data sharing | G5: =INDEX(Sheet2!A:B,MATCH(Sheet1!F5,Sheet2!A:A,0),2) -> Cybersecurity & IT Infrastructure | H5: Techniques like secure enclaves, federated learning, and homomorphic encryption enable collaboration on data without fully exposing it. They are increasingly practical for regulated sectors, but complexity, compute overhead, and immature standards can slow deployment. | I5: [{"Technology_label": "Privacy-enhancing computation (PETs)", "Domain": "Cybersecurity / Data sharing", "Uncertainty_explanation": "Techniques like secure enclaves, federated learning, and homomorphic encryption enable collaboration on data without fully exposing it. They are increasingly practical for regulated sectors, but complexity, compute overhead, and immature standards can slow deployment."}] | J5: 68 | K5: 62 | L5: 68 | M5: 68 | N5: 62 | O5: 62 | P5: 62 | Q5: 62 | R5: 68 | S5: 68 | T5: =AVERAGE(J5:S5) -> 65 | V5: next year | W5: 73.851
A6: 1 | B6: gpt-5.2 | C6: next year | D6: 0.7 | E6: Passkeys and passwordless login | F6: Identity / Security | G6: =INDEX(Sheet2!A:B,MATCH(Sheet1!F6,Sheet2!A:A,0),2) -> Cybersecurity & IT Infrastructure | H6: Passkeys replace passwords with device-based cryptographic credentials, reducing phishing and credential stuffing. Many platforms now support them, but organizational rollout depends on legacy systems, user training, and recovery processes when devices are lost. | I6: [{"Technology_label": "Passkeys and passwordless login", "Domain": "Identity / Security", "Uncertainty_explanation": "Passkeys replace passwords with device-based cryptographic credentials, reducing phishing and credential stuffing. Many platforms now support them, but organizational rollout depends on legacy systems, user training, and recovery processes when devices are lost."}] | J6: 72 | K6: 68 | L6: 72 | M6: 72 | N6: 78 | O6: 72 | P6: 72 | Q6: 72 | R6: 78 | S6: 72 | T6: =AVERAGE(J6:S6) -> 72.8 | V6: (blank)
A7: 1 | B7: gpt-5.2 | C7: next year | D7: 0.7 | E7: Digital product passports | F7: Supply chain / Sustainability | G7: =INDEX(Sheet2!A:B,MATCH(Sheet1!F7,Sheet2!A:A,0),2) -> Logistics, Supply Chain & Retail | H7: Digital passports attach standardized lifecycle information to products (materials, repairs, carbon, provenance) to meet emerging regulations and buyer demands. Adoption is starting in electronics, textiles, and batteries, but data interoperability and supplier participation remain uncertain. | I7: [{"Technology_label": "Digital product passports", "Domain": "Supply chain / Sustainability", "Uncertainty_explanation": "Digital passports attach standardized lifecycle information to products (materials, repairs, carbon, provenance) to meet emerging regulations and buyer demands. Adoption is starting in electronics, textiles, and batteries, but data interoperability and supplier participation remain uncertain."}] | J7: 72 | K7: 62 | L7: 72 | M7: 68 | N7: 72 | O7: 68 | P7: 72 | Q7: 68 | R7: 72 | S7: 72 | T7: =AVERAGE(J7:S7) -> 69.8 | V7: Grand Total | W7: 66.084
A8: 1 | B8: gpt-5.2 | C8: next year | D8: 0.7 | E8: Low-code robotic process automation | F8: Operations / Automation | G8: =INDEX(Sheet2!A:B,MATCH(Sheet1!F8,Sheet2!A:A,0),2) -> Manufacturing, Materials & Industry | H8: Modern RPA combines low-code workflows with AI to automate routine back-office tasks (forms, emails, reconciliations). It can deliver quick ROI, but brittle integrations, process drift, and unclear accountability can limit long-term value. | I8: [{"Technology_label": "Low-code robotic process automation", "Domain": "Operations / Automation", "Uncertainty_explanation": "Modern RPA combines low-code workflows with AI to automate routine back-office tasks (forms, emails, reconciliations). It can deliver quick ROI, but brittle integrations, process drift, and unclear accountability can limit long-term value."}] | J8: 88 | K8: 86 | L8: 85 | M8: 86 | N8: 86 | O8: 86 | P8: 85 | Q8: 88 | R8: 88 | S8: 92 | T8: =AVERAGE(J8:S8) -> 87
A9: 1 | B9: gpt-5.2 | C9: next year | D9: 0.7 | E9: Digital twins for facilities | F9: Built environment / Industrial | G9: =INDEX(Sheet2!A:B,MATCH(Sheet1!F9,Sheet2!A:A,0),2) -> Urban, Civil & Physical Infrastructure | H9: Digital twins are living models of buildings or plants that integrate sensor data to optimize energy use, maintenance, and safety. Tools are maturing rapidly, yet benefits depend on sensor coverage, model upkeep, and integration with existing asset systems. | I9: [{"Technology_label": "Digital twins for facilities", "Domain": "Built environment / Industrial", "Uncertainty_explanation": "Digital twins are living models of buildings or plants that integrate sensor data to optimize energy use, maintenance, and safety. Tools are maturing rapidly, yet benefits depend on sensor coverage, model upkeep, and integration with existing asset systems."}] | J9: 68 | K9: 62 | L9: 62 | M9: 62 | N9: 72 | O9: 62 | P9: 62 | Q9: 68 | R9: 68 | S9: 68 | T9: =AVERAGE(J9:S9) -> 65.4 | V9: Row Labels | W9: Average of avg_probs
A10: 1 | B10: gpt-5.2 | C10: next year | D10: 0.7 | E10: Advanced heat pump retrofits | F10: Energy / Buildings | G10: =INDEX(Sheet2!A:B,MATCH(Sheet1!F10,Sheet2!A:A,0),2) -> Energy, Climate & Environment | H10: Next-generation heat pumps (including cold-climate and hybrid designs) electrify heating and cooling with much higher efficiency than fossil systems. They are ready for scaled adoption, but economics vary by electricity prices, building stock constraints, and installer capacity. | I10: [{"Technology_label": "Advanced heat pump retrofits", "Domain": "Energy / Buildings", "Uncertainty_explanation": "Next-generation heat pumps (including cold-climate and hybrid designs) electrify heating and cooling with much higher efficiency than fossil systems. They are ready for scaled adoption, but economics vary by electricity prices, building stock constraints, and installer capacity."}] | J10: 72 | K10: 72 | L10: 68 | M10: 72 | N10: 68 | O10: 68 | P10: 72 | Q10: 68 | R10: 72 | S10: 62 | T10: =AVERAGE(J10:S10) -> 69.4 | V10: AI & Data Technologies | W10: 77.615625
A11: 1 | B11: gpt-5.2 | C11: next year | D11: 0.7 | E11: Satellite IoT connectivity | F11: Telecom / Remote operations | G11: =INDEX(Sheet2!A:B,MATCH(Sheet1!F11,Sheet2!A:A,0),2) -> Cybersecurity & IT Infrastructure | H11: New low-power satellite networks connect sensors and devices beyond cellular coverage for logistics, utilities, and environmental monitoring. The value is clear for remote assets, while uncertainty lies in service costs, device standards, and long-term constellation reliability. | I11: [{"Technology_label": "Satellite IoT connectivity", "Domain": "Telecom / Remote operations", "Uncertainty_explanation": "New low-power satellite networks connect sensors and devices beyond cellular coverage for logistics, utilities, and environmental monitoring. The value is clear for remote assets, while uncertainty lies in service costs, device standards, and long-term constellation reliability."}] | J11: 78 | K11: 78 | L11: 78 | M11: 78 | N11: 78 | O11: 78 | P11: 78 | Q11: 78 | R11: 78 | S11: 78 | T11: =AVERAGE(J11:S11) -> 78 | V11: Governance, Finance & Law | W11: 71.395238
A12: 1 | B12: gpt-5.2 | C12: next 5–10 years | D12: 0.7 | E12: Autonomous mobile robots at scale | F12: Robotics / Logistics | G12: =INDEX(Sheet2!A:B,MATCH(Sheet1!F12,Sheet2!A:A,0),2) -> Logistics, Supply Chain & Retail | H12: Warehouse and hospital robots will move goods and supplies with minimal human supervision, coordinating through fleet software. Wider adoption depends on safety certification, facility redesign, and labor integration rather than robot hardware alone. | I12: [{"Technology_label": "Autonomous mobile robots at scale", "Domain": "Robotics / Logistics", "Uncertainty_explanation": "Warehouse and hospital robots will move goods and supplies with minimal human supervision, coordinating through fleet software. Wider adoption depends on safety certification, facility redesign, and labor integration rather than robot hardware alone."}] | J12: 78 | K12: 78 | L12: 78 | M12: 82 | N12: 78 | O12: 78 | P12: 78 | Q12: 82 | R12: 78 | S12: 82 | T12: =AVERAGE(J12:S12) -> 79.2 | V12: Cybersecurity & IT Infrastructure | W12: 71.070588
A13: 1 | B13: gpt-5.2 | C13: next 5–10 years | D13: 0.7 | E13: Grid-scale long-duration storage | F13: Energy / Power systems | G13: =INDEX(Sheet2!A:B,MATCH(Sheet1!F13,Sheet2!A:A,0),2) -> Energy, Climate & Environment | H13: Technologies such as iron-air batteries, flow batteries, and thermal storage provide multi-day energy buffering to stabilize renewable-heavy grids. Costs are falling but uncertain winners remain, influenced by supply chains, permitting, and market rules for paying storage. | I13: [{"Technology_label": "Grid-scale long-duration storage", "Domain": "Energy / Power systems", "Uncertainty_explanation": "Technologies such as iron-air batteries, flow batteries, and thermal storage provide multi-day energy buffering to stabilize renewable-heavy grids. Costs are falling but uncertain winners remain, influenced by supply chains, permitting, and market rules for paying storage."}] | J13: 72 | K13: 72 | L13: 72 | M13: 72 | N13: 72 | O13: 75 | P13: 72 | Q13: 72 | R13: 72 | S13: 72 | T13: =AVERAGE(J13:S13) -> 72.3 | V13: Logistics, Supply Chain & Retail | W13: 68.8
A14: 1 | B14: gpt-5.2 | C14: next 5–10 years | D14: 0.7 | E14: Hydrogen for industrial heat | F14: Industry / Decarbonization | G14: =INDEX(Sheet2!A:B,MATCH(Sheet1!F14,Sheet2!A:A,0),2) -> Energy, Climate & Environment | H14: Clean hydrogen can replace fossil fuels for high-temperature processes in steel, chemicals, and refining where electrification is difficult. Adoption will hinge on hydrogen price, infrastructure build-out, and credible emissions accounting. | I14: [{"Technology_label": "Hydrogen for industrial heat", "Domain": "Industry / Decarbonization", "Uncertainty_explanation": "Clean hydrogen can replace fossil fuels for high-temperature processes in steel, chemicals, and refining where electrification is difficult. Adoption will hinge on hydrogen price, infrastructure build-out, and credible emissions accounting."}] | J14: 62 | K14: 55 | L14: 62 | M14: 62 | N14: 62 | O14: 55 | P14: 62 | Q14: 62 | R14: 55 | S14: 62 | T14: =AVERAGE(J14:S14) -> 59.9 | V14: Human Resources, Education & Workplace | W14: 68
A15: 1 | B15: gpt-5.2 | C15: next 5–10 years | D15: 0.7 | E15: Carbon capture for cement | F15: Climate / Heavy industry | G15: =INDEX(Sheet2!A:B,MATCH(Sheet1!F15,Sheet2!A:A,0),2) -> Energy, Climate & Environment | H15: Cement emits CO₂ both from fuel and chemical reactions; capture systems can remove emissions at the kiln or during curing. Deployment is plausible within a decade, but economics depend on carbon policy, storage availability, and plant-by-plant retrofit feasibility. | I15: [{"Technology_label": "Carbon capture for cement", "Domain": "Climate / Heavy industry", "Uncertainty_explanation": "Cement emits CO₂ both from fuel and chemical reactions; capture systems can remove emissions at the kiln or during curing. Deployment is plausible within a decade, but economics depend on carbon policy, storage availability, and plant-by-plant retrofit feasibility."}] | J15: 68 | K15: 65 | L15: 65 | M15: 68 | N15: 68 | O15: 65 | P15: 62 | Q15: 65 | R15: 68 | S15: 65 | T15: =AVERAGE(J15:S15) -> 65.9 | V15: Healthcare, Biotech & Life Sciences | W15: 67.369767
A16: 1 | B16: gpt-5.2 | C16: next 5–10 years | D16: 0.7 | E16: Solid-state battery platforms | F16: Energy / Mobility | G16: =INDEX(Sheet2!A:B,MATCH(Sheet1!F16,Sheet2!A:A,0),2) -> Energy, Climate & Environment | H16: Solid-state batteries replace liquid electrolytes with solid materials to improve safety and potentially increase energy density. Commercialization is progressing, yet manufacturing yield, durability, and cost remain uncertain at mass scale. | I16: [{"Technology_label": "Solid-state battery platforms", "Domain": "Energy / Mobility", "Uncertainty_explanation": "Solid-state batteries replace liquid electrolytes with solid materials to improve safety and potentially increase energy density. Commercialization is progressing, yet manufacturing yield, durability, and cost remain uncertain at mass scale."}] | J16: 65 | K16: 70 | L16: 68 | M16: 72 | N16: 65 | O16: 65 | P16: 68 | Q16: 65 | R16: 68 | S16: 65 | T16: =AVERAGE(J16:S16) -> 67.1 | V16: Urban, Civil & Physical Infrastructure | W16: 65.235714
A17: 1 | B17: gpt-5.2 | C17: next 5–10 years | D17: 0.7 | E17: Quantum sensing for industry | F17: Quantum / Instrumentation | G17: =INDEX(Sheet2!A:B,MATCH(Sheet1!F17,Sheet2!A:A,0),2) -> Space, Quantum & Frontier Technologies | H17: Quantum sensors use quantum effects to measure gravity, magnetic fields, or time with extreme precision, enabling better navigation, subsurface mapping, and equipment monitoring. Adoption is likely in niche high-value use cases first, with uncertainty around ruggedization and total cost. | I17: [{"Technology_label": "Quantum sensing for industry", "Domain": "Quantum / Instrumentation", "Uncertainty_explanation": "Quantum sensors use quantum effects to measure gravity, magnetic fields, or time with extreme precision, enabling better navigation, subsurface mapping, and equipment monitoring. Adoption is likely in niche high-value use cases first, with uncertainty around ruggedization and total cost."}] | J17: 72 | K17: 68 | L17: 72 | M17: 68 | N17: 68 | O17: 72 | P17: 68 | Q17: 68 | R17: 72 | S17: 72 | T17: =AVERAGE(J17:S17) -> 70 | V17: Energy, Climate & Environment | W17: 62.443103
A18: 1 | B18: gpt-5.2 | C18: next 5–10 years | D18: 0.7 | E18: Post-quantum cryptography rollout | F18: Cybersecurity / Cryptography | G18: =INDEX(Sheet2!A:B,MATCH(Sheet1!F18,Sheet2!A:A,0),2) -> Cybersecurity & IT Infrastructure | H18: Post-quantum algorithms are designed to remain secure against future quantum computers and will be embedded into protocols and devices. The transition is complex because systems must be inventoried and upgraded, and performance impacts and interoperability issues are still being worked out. | I18: [{"Technology_label": "Post-quantum cryptography rollout", "Domain": "Cybersecurity / Cryptography", "Uncertainty_explanation": "Post-quantum algorithms are designed to remain secure against future quantum computers and will be embedded into protocols and devices. The transition is complex because systems must be inventoried and upgraded, and performance impacts and interoperability issues are still being worked out."}] | J18: 85 | K18: 85 | L18: 85 | M18: 85 | N18: 85 | O18: 85 | P18: 85 | Q18: 85 | R18: 85 | S18: 85 | T18: =AVERAGE(J18:S18) -> 85 | V18: Manufacturing, Materials & Industry | W18: 58.946429
A19: 1 | B19: gpt-5.2 | C19: next 5–10 years | D19: 0.7 | E19: Precision fermentation ingredients | F19: Food / Biomanufacturing | G19: =INDEX(Sheet2!A:B,MATCH(Sheet1!F19,Sheet2!A:A,0),2) -> Healthcare, Biotech & Life Sciences | H19: Microbes can be engineered to produce proteins, fats, and specialty ingredients with lower land use and more stable supply. Scaling depends on bioreactor capacity, regulatory pathways, and consumer acceptance of labeling and claims. | I19: [{"Technology_label": "Precision fermentation ingredients", "Domain": "Food / Biomanufacturing", "Uncertainty_explanation": "Microbes can be engineered to produce proteins, fats, and specialty ingredients with lower land use and more stable supply. Scaling depends on bioreactor capacity, regulatory pathways, and consumer acceptance of labeling and claims."}] | J19: 78 | K19: 78 | L19: 78 | M19: 78 | N19: 78 | O19: 78 | P19: 78 | Q19: 78 | R19: 78 | S19: 78 | T19: =AVERAGE(J19:S19) -> 78 | V19: Space, Quantum & Frontier Technologies | W19: 47.026087
A20: 1 | B20: gpt-5.2 | C20: next 5–10 years | D20: 0.7 | E20: Neuro-symbolic decision systems | F20: AI / Decision support | G20: =INDEX(Sheet2!A:B,MATCH(Sheet1!F20,Sheet2!A:A,0),2) -> AI & Data Technologies | H20: Neuro-symbolic AI combines pattern-learning (neural networks) with explicit rules and logic to improve reliability, traceability, and compliance. It could be valuable in regulated decision-making, though tools and talent are still emerging and integration with workflows is non-trivial. | I20: [{"Technology_label": "Neuro-symbolic decision systems", "Domain": "AI / Decision support", "Uncertainty_explanation": "Neuro-symbolic AI combines pattern-learning (neural networks) with explicit rules and logic to improve reliability, traceability, and compliance. It could be valuable in regulated decision-making, though tools and talent are still emerging and integration with workflows is non-trivial."}] | J20: 67 | K20: 62 | L20: 62 | M20: 62 | N20: 62 | O20: 68 | P20: 62 | Q20: 62 | R20: 62 | S20: 62 | T20: =AVERAGE(J20:S20) -> 63.1 | V20: (blank)
A21: 1 | B21: gpt-5.2 | C21: next 5–10 years | D21: 0.7 | E21: Immersive telepresence workspaces | F21: Collaboration / XR | G21: =INDEX(Sheet2!A:B,MATCH(Sheet1!F21,Sheet2!A:A,0),2) -> Human Resources, Education & Workplace | H21: Lightweight mixed-reality devices and spatial computing will enable richer remote collaboration for design, training, and operations support. Adoption depends on comfort, content ecosystems, and whether productivity gains outweigh device and change-management costs. | I21: [{"Technology_label": "Immersive telepresence workspaces", "Domain": "Collaboration / XR", "Uncertainty_explanation": "Lightweight mixed-reality devices and spatial computing will enable richer remote collaboration for design, training, and operations support. Adoption depends on comfort, content ecosystems, and whether productivity gains outweigh device and change-management costs."}] | J21: 68 | K21: 68 | L21: 72 | M21: 68 | N21: 68 | O21: 68 | P21: 62 | Q21: 68 | R21: 68 | S21: 68 | T21: =AVERAGE(J21:S21) -> 67.8 | V21: Grand Total | W21: 66.084
A22: 1 | B22: gpt-5.2 | C22: next 20–40 years | D22: 0.7 | E22: Practical fusion power plants | F22: Energy | G22: =INDEX(Sheet2!A:B,MATCH(Sheet1!F22,Sheet2!A:A,0),2) -> Energy, Climate & Environment | H22: Fusion aims to generate electricity by fusing light atoms, potentially offering abundant low-carbon power with minimal long-lived waste. The major uncertainties are achieving sustained net energy at commercial scale, materials that survive extreme conditions, and building plants at competitive cost. | I22: [{"Technology_label": "Practical fusion power plants", "Domain": "Energy", "Uncertainty_explanation": "Fusion aims to generate electricity by fusing light atoms, potentially offering abundant low-carbon power with minimal long-lived waste. The major uncertainties are achieving sustained net energy at commercial scale, materials that survive extreme conditions, and building plants at competitive cost."}] | J22: 35 | K22: 35 | L22: 35 | M22: 35 | N22: 35 | O22: 35 | P22: 45 | Q22: 35 | R22: 35 | S22: 35 | T22: =AVERAGE(J22:S22) -> 36
A23: 1 | B23: gpt-5.2 | C23: next 20–40 years | D23: 0.7 | E23: Fault-tolerant quantum computing | F23: Computing / Quantum | G23: =INDEX(Sheet2!A:B,MATCH(Sheet1!F23,Sheet2!A:A,0),2) -> Space, Quantum & Frontier Technologies | H23: Fault-tolerant quantum computers would run long, accurate computations for chemistry, materials, and optimization beyond today’s capabilities. Timelines are uncertain due to error correction overhead, hardware scalability, and the need for compelling applications that justify operational cost. | I23: [{"Technology_label": "Fault-tolerant quantum computing", "Domain": "Computing / Quantum", "Uncertainty_explanation": "Fault-tolerant quantum computers would run long, accurate computations for chemistry, materials, and optimization beyond today’s capabilities. Timelines are uncertain due to error correction overhead, hardware scalability, and the need for compelling applications that justify operational cost."}] | J23: 55 | K23: 62 | L23: 55 | M23: 65 | N23: 55 | O23: 55 | P23: 55 | Q23: 55 | R23: 55 | S23: 55 | T23: =AVERAGE(J23:S23) -> 56.7
A24: 1 | B24: gpt-5.2 | C24: next 20–40 years | D24: 0.7 | E24: Brain-computer interface ecosystems | F24: Health / Human-computer interaction | G24: =INDEX(Sheet2!A:B,MATCH(Sheet1!F24,Sheet2!A:A,0),2) -> Healthcare, Biotech & Life Sciences | H24: BCIs translate neural activity into commands for communication, control, or rehabilitation, potentially expanding to non-medical productivity uses over decades. Adoption will depend on safety, long-term stability, privacy regulation, and social acceptance—especially for implanted systems. | I24: [{"Technology_label": "Brain-computer interface ecosystems", "Domain": "Health / Human-computer interaction", "Uncertainty_explanation": "BCIs translate neural activity into commands for communication, control, or rehabilitation, potentially expanding to non-medical productivity uses over decades. Adoption will depend on safety, long-term stability, privacy regulation, and social acceptance—especially for implanted systems."}] | J24: 72 | K24: 65 | L24: 62 | M24: 68 | N24: 65 | O24: 72 | P24: 68 | Q24: 68 | R24: 65 | S24: 65 | T24: =AVERAGE(J24:S24) -> 67
A25: 1 | B25: gpt-5.2 | C25: next 20–40 years | D25: 0.7 | E25: General-purpose autonomous AI agents | F25: AI / Automation | G25: =INDEX(Sheet2!A:B,MATCH(Sheet1!F25,Sheet2!A:A,0),2) -> AI & Data Technologies | H25: More capable AI agents could plan, negotiate, and execute complex multi-step tasks across software and physical systems with limited supervision. The uncertainty is less about raw capability and more about alignment, liability, auditing, and governance to prevent harmful or opaque actions. | I25: [{"Technology_label": "General-purpose autonomous AI agents", "Domain": "AI / Automation", "Uncertainty_explanation": "More capable AI agents could plan, negotiate, and execute complex multi-step tasks across software and physical systems with limited supervision. The uncertainty is less about raw capability and more about alignment, liability, auditing, and governance to prevent harmful or opaque actions."}] | J25: 85 | K25: 85 | L25: 85 | M25: 78 | N25: 75 | O25: 80 | P25: 85 | Q25: 78 | R25: 85 | S25: 85 | T25: =AVERAGE(J25:S25) -> 82.1
A26: 1 | B26: gpt-5.2 | C26: next 20–40 years | D26: 0.7 | E26: Molecular nanomanufacturing concepts | F26: Advanced manufacturing / Nanotech | G26: =INDEX(Sheet2!A:B,MATCH(Sheet1!F26,Sheet2!A:A,0),2) -> Manufacturing, Materials & Industry | H26: Nanomanufacturing envisions building materials and devices by positioning molecules or nanoscale components with extreme precision, enabling novel properties and ultra-efficient production. It remains speculative, with major technical hurdles in control, error rates, and scalable fabrication. | I26: [{"Technology_label": "Molecular nanomanufacturing concepts", "Domain": "Advanced manufacturing / Nanotech", "Uncertainty_explanation": "Nanomanufacturing envisions building materials and devices by positioning molecules or nanoscale components with extreme precision, enabling novel properties and ultra-efficient production. It remains speculative, with major technical hurdles in control, error rates, and scalable fabrication."}] | J26: 22 | K26: 18 | L26: 20 | M26: 25 | N26: 25 | O26: 25 | P26: 18 | Q26: 25 | R26: 25 | S26: 25 | T26: =AVERAGE(J26:S26) -> 22.8
A27: 1 | B27: gpt-5.2 | C27: next 20–40 years | D27: 0.7 | E27: Programmable matter and metamaterials | F27: Materials / Defense & infrastructure | G27: =INDEX(Sheet2!A:B,MATCH(Sheet1!F27,Sheet2!A:A,0),2) -> Manufacturing, Materials & Industry | H27: Metamaterials and programmable matter are engineered structures whose properties (e.g., strength, optics, acoustics) can be tuned or reconfigured. Over decades they could reshape sensing, communications, and construction, but breakthroughs in manufacturing, durability, and cost are required. | I27: [{"Technology_label": "Programmable matter and metamaterials", "Domain": "Materials / Defense & infrastructure", "Uncertainty_explanation": "Metamaterials and programmable matter are engineered structures whose properties (e.g., strength, optics, acoustics) can be tuned or reconfigured. Over decades they could reshape sensing, communications, and construction, but breakthroughs in manufacturing, durability, and cost are required."}] | J27: 72 | K27: 78 | L27: 72 | M27: 72 | N27: 78 | O27: 72 | P27: 72 | Q27: 72 | R27: 72 | S27: 72 | T27: =AVERAGE(J27:S27) -> 73.2
A28: 1 | B28: gpt-5.2 | C28: next 20–40 years | D28: 0.7 | E28: Organ-scale bioprinting | F28: Biotech / Healthcare | G28: =INDEX(Sheet2!A:B,MATCH(Sheet1!F28,Sheet2!A:A,0),2) -> Healthcare, Biotech & Life Sciences | H28: Bioprinting aims to fabricate tissues and eventually full organs using living cells and scaffolds to address transplant shortages. Progress is steady for simpler tissues, while full organ function, vascularization, and regulatory validation make timelines highly uncertain. | I28: [{"Technology_label": "Organ-scale bioprinting", "Domain": "Biotech / Healthcare", "Uncertainty_explanation": "Bioprinting aims to fabricate tissues and eventually full organs using living cells and scaffolds to address transplant shortages. Progress is steady for simpler tissues, while full organ function, vascularization, and regulatory validation make timelines highly uncertain."}] | J28: 55 | K28: 55 | L28: 55 | M28: 55 | N28: 55 | O28: 55 | P28: 45 | Q28: 55 | R28: 55 | S28: 55 | T28: =AVERAGE(J28:S28) -> 54
A29: 1 | B29: gpt-5.2 | C29: next 20–40 years | D29: 0.7 | E29: Climate restoration interventions | F29: Climate / Earth systems | G29: =INDEX(Sheet2!A:B,MATCH(Sheet1!F29,Sheet2!A:A,0),2) -> Energy, Climate & Environment | H29: Beyond emissions cuts, large-scale interventions such as ocean alkalinity enhancement or stratospheric aerosol approaches could reduce warming or remove CO₂. Adoption is uncertain due to governance, uneven regional impacts, monitoring challenges, and ethical concerns. | I29: [{"Technology_label": "Climate restoration interventions", "Domain": "Climate / Earth systems", "Uncertainty_explanation": "Beyond emissions cuts, large-scale interventions such as ocean alkalinity enhancement or stratospheric aerosol approaches could reduce warming or remove CO₂. Adoption is uncertain due to governance, uneven regional impacts, monitoring challenges, and ethical concerns."}] | J29: 55 | K29: 55 | L29: 55 | M29: 55 | N29: 55 | O29: 55 | P29: 55 | Q29: 55 | R29: 55 | S29: 55 | T29: =AVERAGE(J29:S29) -> 55
A30: 1 | B30: gpt-5.2 | C30: next 20–40 years | D30: 0.7 | E30: Space-based solar power | F30: Energy / Space | G30: =INDEX(Sheet2!A:B,MATCH(Sheet1!F30,Sheet2!A:A,0),2) -> Space, Quantum & Frontier Technologies | H30: Space solar power would collect solar energy in orbit and beam it to Earth, potentially providing constant renewable electricity. Feasibility depends on launch costs, wireless power transmission safety, orbital debris management, and international regulation. | I30: [{"Technology_label": "Space-based solar power", "Domain": "Energy / Space", "Uncertainty_explanation": "Space solar power would collect solar energy in orbit and beam it to Earth, potentially providing constant renewable electricity. Feasibility depends on launch costs, wireless power transmission safety, orbital debris management, and international regulation."}] | J30: 35 | K30: 35 | L30: 35 | M30: 35 | N30: 35 | O30: 35 | P30: 35 | Q30: 35 | R30: 35 | S30: 35 | T30: =AVERAGE(J30:S30) -> 35
A31: 1 | B31: gpt-5.2 | C31: next 20–40 years | D31: 0.7 | E31: Autonomous self-healing infrastructure | F31: Infrastructure / Smart cities | G31: =INDEX(Sheet2!A:B,MATCH(Sheet1!F31,Sheet2!A:A,0),2) -> Urban, Civil & Physical Infrastructure | H31: Future infrastructure could use embedded sensors, robotics, and self-healing materials to detect damage and repair roads, bridges, pipes, or grids with minimal downtime. The uncertainties include system complexity, cybersecurity risks, and whether lifecycle savings justify high upfront investment. | I31: [{"Technology_label": "Autonomous self-healing infrastructure", "Domain": "Infrastructure / Smart cities", "Uncertainty_explanation": "Future infrastructure could use embedded sensors, robotics, and self-healing materials to detect damage and repair roads, bridges, pipes, or grids with minimal downtime. The uncertainties include system complexity, cybersecurity risks, and whether lifecycle savings justify high upfront investment."}] | J31: 62 | K31: 62 | L31: 68 | M31: 62 | N31: 62 | O31: 68 | P31: 68 | Q31: 68 | R31: 62 | S31: 68 | T31: =AVERAGE(J31:S31) -> 65
A32: 2 | B32: gpt-5.2 | C32: next year | D32: 0.7 | E32: Private enterprise AI copilots | F32: Enterprise software / AI | G32: =INDEX(Sheet2!A:B,MATCH(Sheet1!F32,Sheet2!A:A,0),2) -> AI & Data Technologies | H32: Organization-specific AI assistants run in private cloud/on‑prem and connect to internal documents, tickets, and workflows (HR, finance, legal, IT). They can draft, summarize, and take actions with audit trails, but adoption hinges on data governance, access control, and measurable productivity gains. | I32: [{"Technology_label": "Private enterprise AI copilots", "Domain": "Enterprise software / AI", "Uncertainty_explanation": "Organization-specific AI assistants run in private cloud/on‑prem and connect to internal documents, tickets, and workflows (HR, finance, legal, IT). They can draft, summarize, and take actions with audit trails, but adoption hinges on data governance, access control, and measurable productivity gains."}] | J32: 78 | K32: 78 | L32: 78 | M32: 78 | N32: 78 | O32: 78 | P32: 78 | Q32: 78 | R32: 78 | S32: 78 | T32: =AVERAGE(J32:S32) -> 78
A33: 2 | B33: gpt-5.2 | C33: next year | D33: 0.7 | E33: AI agents for workflows | F33: Operations / Automation | G33: =INDEX(Sheet2!A:B,MATCH(Sheet1!F33,Sheet2!A:A,0),2) -> Manufacturing, Materials & Industry | H33: Task-focused AI “agents” can plan and execute multi-step processes (e.g., procurement requests, incident triage, customer follow-up) across multiple tools. The technology is usable now in bounded settings, yet reliability, security permissions, and accountability for errors remain key adoption barriers. | I33: [{"Technology_label": "AI agents for workflows", "Domain": "Operations / Automation", "Uncertainty_explanation": "Task-focused AI “agents” can plan and execute multi-step processes (e.g., procurement requests, incident triage, customer follow-up) across multiple tools. The technology is usable now in bounded settings, yet reliability, security permissions, and accountability for errors remain key adoption barriers."}] | J33: 78 | K33: 78 | L33: 78 | M33: 72 | N33: 78 | O33: 78 | P33: 72 | Q33: 78 | R33: 78 | S33: 78 | T33: =AVERAGE(J33:S33) -> 76.8
... A301: 10 | B301: gpt-5.2 | C301: next 20–40 years | D301: 0.7 | E301: Cognitive digital twins of organizations | F301: Governance / Decision intelligence | G301: =INDEX(Sheet2!A:B,MATCH(Sheet1!F301,Sheet2!A:A,0),2) -> Governance, Finance & Law | H301: Beyond asset twins, cognitive organizational twins would simulate policies, incentives, and operational decisions using integrated data, behavioral models, and AI to test interventions before deployment. Adoption depends on trustworthy modeling, bias controls, transparency, and legal accountability for AI-informed decisions. | I301: [{"Technology_label": "Cognitive digital twins of organizations", "Domain": "Governance / Decision intelligence", "Uncertainty_explanation": "Beyond asset twins, cognitive organizational twins would simulate policies, incentives, and operational decisions using integrated data, behavioral models, and AI to test interventions before deployment. Adoption depends on trustworthy modeling, bias controls, transparency, and legal accountability for AI-informed decisions."}] | J301: 62 | K301: 68 | L301: 62 | M301: 62 | N301: 72 | O301: 62 | P301: 62 | Q301: 62 | R301: 62 | S301: 62 | T301: =AVERAGE(J301:S301) -> 63.6

Sheet Sheet2
A1: Entry | B1: Category
A2: AI / Edge computing | B2: AI & Data Technologies
A3: AI / Knowledge management | B3: AI & Data Technologies
A4: Data / Privacy | B4: Governance, Finance & Law
A5: Cybersecurity / Data sharing | B5: Cybersecurity & IT Infrastructure
A6: Identity / Security | B6: Cybersecurity & IT Infrastructure
A7: Supply chain / Sustainability | B7: Logistics, Supply Chain & Retail
A8: Operations / Automation | B8: Manufacturing, Materials & Industry
A9: Built environment / Industrial | B9: Urban, Civil & Physical Infrastructure
A10: Energy / Buildings | B10: Energy, Climate & Environment
A11: Telecom / Remote operations | B11: Cybersecurity & IT Infrastructure
A12: Robotics / Logistics | B12: Logistics, Supply Chain & Retail
... A202: Governance / Decision intelligence | B202: Governance, Finance & Law
